Workbook
Name Slicer_DIVISION_DESCRIPTION: #N/A

Sheet Pivot Table
A3: DIVISION DESCRIPTION | B3: Sum of TOTAL BUDGETED AMOUNT
A4: Patrol Services | B4: 1224603400
A5: Chicago Fire Department | B5: 556547794
A6: Chicago-O'Hare International Airport | B6: 197854959
A7: Bureau of Operations and Distribution | B7: 169911417
A8: Bureau of Counter-Terrorism | B8: 143287614
A9: Bureau of Sanitation | B9: 127338664
A10: Division of In-House Construction | B10: 94835261
A11: Office of Emergency Management and Communications | B11: 81824516
A12: Chicago Public Library | B12: 77548650
A13: Bureau of Detectives | B13: 68753448
A14: Grand Total | B14: 2742505723

Sheet Dashboard
A1: CHICAGO CITY BUDGET DASHBOARD
A2: KPI Summary
A3: Total Budget | B3: =SUM('Raw Data'!V:V) -> 3910809184
A4: Total Positions | B4: =SUM('Raw Data'!T:T) -> 7186
A5: AVG. Pay Rate | B5: =AVERAGE('Raw Data'!U:U) -> 100052.25
A6: Highest Salary | B6: =MAX('Raw Data'!V:V) -> 238969296
A7: Top 10 Divisions
A8: Division | B8: Total Budget | C8: Headcount | D8: Cost Per Position | E8: % Of Budget
A9: Patrol Services | B9: =SUMIF('Raw Data'!I:I,"Patrol Services",'Raw Data'!V:V) -> 1224603400 | C9: =COUNTIF('Raw Data'!I:I,"Patrol Services") -> 102 | D9: =B9/C9 -> 12005916 | E9: =B9/SUM('Raw Data'!V:V) -> 0.313133
A10: Chicago Fire Department | B10: =SUMIF('Raw Data'!I:I,"Chicago Fire Department",'Raw Data'!V:V) -> 556547794 | C10: =COUNTIF('Raw Data'!I:I,"Chicago Fire Department") -> 406 | D10: =B10/C10 -> 1370807.4 | E10: =B10/SUM('Raw Data'!V:V) -> 0.14231014
A11: Chicago-O'Hare International Airport | B11: =SUMIF('Raw Data'!I:I,"Chicago-O'Hare International Airport",'Raw Data'!V:V) -> 197854959 | C11: =COUNTIF('Raw Data'!I:I,"Chicago-O'Hare International Airport") -> 573 | D11: =B11/C11 -> 345296.61 | E11: =B11/SUM('Raw Data'!V:V) -> 0.050591821
A12: Bureau of Operations and Distribution | B12: =SUMIF('Raw Data'!I:I,"Bureau of Operations and Distribution",'Raw Data'!V:V) -> 169911417 | C12: =COUNTIF('Raw Data'!I:I,"Bureau of Operations and Distribution") -> 165 | D12: =B12/C12 -> 1029766.2 | E12: =B12/SUM('Raw Data'!V:V) -> 0.043446614
A13: Bureau of Counter-Terrorism | B13: =SUMIF('Raw Data'!I:I,"Bureau of Counter-Terrorism",'Raw Data'!V:V) -> 143287614 | C13: =COUNTIF('Raw Data'!I:I,"Bureau of Counter-Terrorism") -> 259 | D13: =B13/C13 -> 553234.03 | E13: =B13/SUM('Raw Data'!V:V) -> 0.036638866
A14: Bureau of Sanitation | B14: =SUMIF('Raw Data'!I:I,"Bureau of Sanitation",'Raw Data'!V:V) -> 127338664 | C14: =COUNTIF('Raw Data'!I:I,"Bureau of Sanitation") -> 88 | D14: =B14/C14 -> 1447030.3 | E14: =B14/SUM('Raw Data'!V:V) -> 0.032560695
A15: Division of In-House Construction | B15: =SUMIF('Raw Data'!I:I,"Division of In-House Construction",'Raw Data'!V:V) -> 94835261 | C15: =COUNTIF('Raw Data'!I:I,"Division of In-House Construction") -> 124 | D15: =B15/C15 -> 764800.49 | E15: =B15/SUM('Raw Data'!V:V) -> 0.024249524
A16: Office of Emergency Management and Communications | B16: =SUMIF('Raw Data'!I:I,"Office of Emergency Management and Communications",'Raw Data'!V:V) -> 81824516 | C16: =COUNTIF('Raw Data'!I:I,"Office of Emergency Management and Communications") -> 200 | D16: =B16/C16 -> 409122.58 | E16: =B16/SUM('Raw Data'!V:V) -> 0.020922656
A17: Chicago Public Library | B17: =SUMIF('Raw Data'!I:I,"Chicago Public Library",'Raw Data'!V:V) -> 77548650 | C17: =COUNTIF('Raw Data'!I:I,"Chicago Public Library") -> 196 | D17: =B17/C17 -> 395656.38 | E17: =B17/SUM('Raw Data'!V:V) -> 0.019829311
A18: Bureau of Detectives | B18: =SUMIF('Raw Data'!I:I,"Bureau of Detectives",'Raw Data'!V:V) -> 68753448 | C18: =COUNTIF('Raw Data'!I:I,"Bureau of Detectives") -> 165 | D18: =B18/C18 -> 416687.56 | E18: =B18/SUM('Raw Data'!V:V) -> 0.017580364
A51: DIVISION DESCRIPTION | B51: Sum of TOTAL BUDGETED AMOUNT | C51: Sum of TOTAL BUDGETED UNIT
A52: Patrol Services | B52: 1224603400 | C52: 71693
A53: Chicago Fire Department | B53: 556547794 | C53: 5123
A54: Chicago-O'Hare International Airport | B54: 197854959 | C54: 319472
A55: Bureau of Operations and Distribution | B55: 169911417 | C55: 1365248
A56: Bureau of Counter-Terrorism | B56: 143287614 | C56: 21611
A57: Bureau of Sanitation | B57: 127338664 | C57: 57299
A58: Division of In-House Construction | B58: 94835261 | C58: 454601
A59: Office of Emergency Management and Communications | B59: 81824516 | C59: 204480
A60: Chicago Public Library | B60: 77548650 | C60: 355442
A61: Bureau of Detectives | B61: 68753448 | C61: 12922
A62: Bureau of Fleet Operations | B62: 68737489 | C62: 608
A63: Office of Constitutional Policing and Reform | B63: 65833298 | C63: 25553
... A211: Grand Total | B211: 3910809184 | C211: 3270432

Sheet Raw Data
A1: FUND TYPE | B1: DEPARTMENT CODE | C1: DEPARTMENT DESCRIPTION | D1: FUND CODE | E1: FUND DESCRIPTION | F1: ORGANIZATION CODE | G1: ORGANIZATION DESCRIPTION | H1: DIVISION CODE | I1: DIVISION DESCRIPTION | J1: SECTION CODE | K1: SECTION DESCRIPTION | L1: SUBSECTION CODE | M1: SUB-SECTION DESCRIPTION | N1: SCHEDULE / GRADE | O1: BARGAINING UNIT | P1: TITLE CODE | Q1: TITLE DESCRIPTION | R1: BUDGETED UNIT | S1: TOTAL BUDGETED UNIT | T1: POSITION CONTROL | U1: BUDGETED PAY RATE | V1: TOTAL BUDGETED AMOUNT | W1: Cost Per Position | X1: % Of Total Budget
A2: LOCAL | B2: 1 | C2: Office of the Mayor | D2: 100 | E2: Corporate Fund | F2: 1005 | G2: Office of the Mayor | H2: 2005 | I2: Office of the Mayor | J2: 3005 | K2: Executive | L2: 0 | N2: 1 00 | O2: 9 | P2: 9901 | Q2: Mayor | R2: Annual | S2: 1 | T2: 1 | U2: 221052 | V2: 221052 | W2: =V2/T2 -> 221052 | X2: =V2/SUM($V$2:$V$10000) -> 5.6523341e-05
A3: LOCAL | B3: 1 | C3: Office of the Mayor | D3: 100 | E3: Corporate Fund | F3: 1005 | G3: Office of the Mayor | H3: 2005 | I3: Office of the Mayor | J3: 3005 | K3: Executive | L3: 0 | N3: 1 00 | O3: 9 | P3: 9877 | Q3: Director - Mayor's Office | R3: Annual | S3: 1 | T3: 1 | U3: 142272 | V3: 142272
A4: LOCAL | B4: 1 | C4: Office of the Mayor | D4: 100 | E4: Corporate Fund | F4: 1005 | G4: Office of the Mayor | H4: 2005 | I4: Office of the Mayor | J4: 3005 | K4: Executive | L4: 0 | N4: 1 00 | O4: 9 | P4: 9875 | Q4: Senior Project Manager - Mayor's Office | R4: Annual | S4: 1 | T4: 1 | U4: 123600 | V4: 123600
A5: LOCAL | B5: 1 | C5: Office of the Mayor | D5: 100 | E5: Corporate Fund | F5: 1005 | G5: Office of the Mayor | H5: 2005 | I5: Office of the Mayor | J5: 3005 | K5: Executive | L5: 0 | N5: 1 00 | O5: 9 | P5: 9869 | Q5: Senior Advisor to the Mayor | R5: Annual | S5: 1 | T5: 1 | U5: 195000 | V5: 195000
A6: LOCAL | B6: 1 | C6: Office of the Mayor | D6: 100 | E6: Corporate Fund | F6: 1005 | G6: Office of the Mayor | H6: 2005 | I6: Office of the Mayor | J6: 3005 | K6: Executive | L6: 0 | N6: 1 00 | O6: 0 | P6: 9637 | Q6: Administrative Assistant | R6: Annual | S6: 1 | T6: 1 | U6: 110464 | V6: 110464
A7: LOCAL | B7: 1 | C7: Office of the Mayor | D7: 100 | E7: Corporate Fund | F7: 1005 | G7: Office of the Mayor | H7: 2005 | I7: Office of the Mayor | J7: 3006 | K7: Correspondence | L7: 0 | N7: 1 00 | O7: 9 | P7: 9874 | Q7: Project Manager - Mayor's Office | R7: Annual | S7: 1 | T7: 1 | U7: 106632 | V7: 106632
A8: LOCAL | B8: 1 | C8: Office of the Mayor | D8: 100 | E8: Corporate Fund | F8: 1005 | G8: Office of the Mayor | H8: 2005 | I8: Office of the Mayor | J8: 3007 | K8: Scheduling and Advance | L8: 0 | N8: 1 00 | O8: 9 | P8: 9870 | Q8: Advance | R8: Annual | S8: 1 | T8: 1 | U8: 74592 | V8: 74592
A9: LOCAL | B9: 1 | C9: Office of the Mayor | D9: 100 | E9: Corporate Fund | F9: 1005 | G9: Office of the Mayor | H9: 2005 | I9: Office of the Mayor | J9: 3007 | K9: Scheduling and Advance | L9: 0 | N9: 1 00 | O9: 9 | P9: 9855 | Q9: Assistant Director - Mayor's Office | R9: Annual | S9: 1 | T9: 1 | U9: 90048 | V9: 90048
A10: LOCAL | B10: 1 | C10: Office of the Mayor | D10: 100 | E10: Corporate Fund | F10: 1005 | G10: Office of the Mayor | H10: 2005 | I10: Office of the Mayor | J10: 3010 | K10: Administrative | L10: 0 | N10: 1 00 | O10: 9 | P10: 9899 | Q10: Chief of Staff | R10: Annual | S10: 1 | T10: 1 | U10: 217044 | V10: 217044
A11: LOCAL | B11: 1 | C11: Office of the Mayor | D11: 100 | E11: Corporate Fund | F11: 1005 | G11: Office of the Mayor | H11: 2005 | I11: Office of the Mayor | J11: 3010 | K11: Administrative | L11: 0 | N11: 1 00 | O11: 9 | P11: 9898 | Q11: Deputy Chief of Staff | R11: Annual | S11: 1 | T11: 1 | U11: 183180 | V11: 183180
A12: LOCAL | B12: 1 | C12: Office of the Mayor | D12: 100 | E12: Corporate Fund | F12: 1005 | G12: Office of the Mayor | H12: 2005 | I12: Office of the Mayor | J12: 3010 | K12: Administrative | L12: 0 | N12: 1 00 | O12: 9 | P12: 9889 | Q12: First Deputy Chief of Staff | R12: Annual | S12: 1 | T12: 1 | U12: 197760 | V12: 197760
A13: LOCAL | B13: 1 | C13: Office of the Mayor | D13: 100 | E13: Corporate Fund | F13: 1005 | G13: Office of the Mayor | H13: 2005 | I13: Office of the Mayor | J13: 3010 | K13: Administrative | L13: 0 | N13: 1 00 | O13: 9 | P13: 9877 | Q13: Director - Mayor's Office | R13: Annual | S13: 1 | T13: 1 | U13: 135912 | V13: 135912
A14: LOCAL | B14: 1 | C14: Office of the Mayor | D14: 100 | E14: Corporate Fund | F14: 1005 | G14: Office of the Mayor | H14: 2005 | I14: Office of the Mayor | J14: 3010 | K14: Administrative | L14: 0 | N14: 1 00 | O14: 9 | P14: 9874 | Q14: Project Manager - Mayor's Office | R14: Annual | S14: 1 | T14: 1 | U14: 92172 | V14: 92172
... A147: LOCAL | B147: 3 | C147: Office of Inspector General | D147: 100 | E147: Corporate Fund | F147: 1005 | G147: Office of Inspector General | H147: 2005 | I147: Office of Inspector General | J147: 3045 | K147: Information Technology and Analytics | L147: 0 | N147: X 33 | O147: 0 | P147: 1717 | Q147: Chief Data and Information Analyst | R147: Annual | S147: 1 | T147: 1 | U147: 153384 | V147: 153384
A148: LOCAL | B148: 3 | C148: Office of Inspector General | D148: 100 | E148: Corporate Fund | F148: 1005 | G148: Office of Inspector General | H148: 2005 | I148: Office of Inspector General | J148: 3045 | K148: Information Technology and Analytics | L148: 0 | N148: BX 17 | O148: 10 | P148: 06M3 | Q148: Web Developer/Administrator (OIG) | R148: Annual | S148: 1 | T148: 1 | U148: 103488 | V148: 103488
A149: LOCAL | B149: 3 | C149: Office of Inspector General | D149: 100 | E149: Corporate Fund | F149: 1005 | G149: Office of Inspector General | H149: 2005 | I149: Office of Inspector General | J149: 3045 | K149: Information Technology and Analytics | L149: 0 | N149: GY 09 | O149: 20 | P149: 06A7 | Q149: IT Security Analyst-IG | R149: Annual | S149: 1 | T149: 1 | U149: 97332 | V149: 97332
A150: LOCAL | B150: 3 | C150: Office of Inspector General | D150: 100 | E150: Corporate Fund | F150: 1005 | G150: Office of Inspector General | H150: 2005 | I150: Office of Inspector General | J150: 3045 | K150: Information Technology and Analytics | L150: 0 | N150: BX 17 | O150: 10 | P150: 06A4 | Q150: Data Services Administrator-Excluded | R150: Annual | S150: 1 | T150: 1 | U150: 85128 | V150: 85128
A151: LOCAL | B151: 3 | C151: Office of Inspector General | D151: 100 | E151: Corporate Fund | F151: 1005 | G151: Office of Inspector General | H151: 2005 | I151: Office of Inspector General | J151: 3045 | K151: Information Technology and Analytics | L151: 0 | N151: BX 13 | O151: 10 | P151: 645 | Q151: Technical Support Administrator - IG | R151: Annual | S151: 1 | T151: 1 | U151: 60660 | V151: 60660
A152: LOCAL | B152: 3 | C152: Office of Inspector General | D152: 100 | E152: Corporate Fund | F152: 1005 | G152: Office of Inspector General | H152: 2005 | I152: Office of Inspector General | J152: 3045 | K152: Information Technology and Analytics | L152: 0 | N152: GY 09 | O152: 10 | P152: 641 | Q152: Forensic Data Analyst | R152: Annual | S152: 1 | T152: 1 | U152: 101628 | V152: 101628
A153: LOCAL | B153: 3 | C153: Office of Inspector General | D153: 100 | E153: Corporate Fund | F153: 1005 | G153: Office of Inspector General | H153: 2005 | I153: Office of Inspector General | J153: 3045 | K153: Information Technology and Analytics | L153: 0 | N153: GY 09 | O153: 10 | P153: 641 | Q153: Forensic Data Analyst | R153: Annual | S153: 2 | T153: 1 | U153: 97332 | V153: 194664
A154: LOCAL | B154: 3 | C154: Office of Inspector General | D154: 100 | E154: Corporate Fund | F154: 1005 | G154: Office of Inspector General | H154: 2005 | I154: Office of Inspector General | J154: 3045 | K154: Information Technology and Analytics | L154: 0 | N154: GY 09 | O154: 10 | P154: 641 | Q154: Forensic Data Analyst | R154: Annual | S154: 1 | T154: 1 | U154: 89112 | V154: 89112
A155: LOCAL | B155: 3 | C155: Office of Inspector General | D155: 100 | E155: Corporate Fund | F155: 1005 | G155: Office of Inspector General | H155: 2005 | I155: Office of Inspector General | J155: 3045 | K155: Information Technology and Analytics | L155: 0 | N155: 1 00 | O155: 0 | P155: 15 | Q155: Schedule Salary Adjustments | R155: Annual | S155: 0 | T155: 0 | U155: 44675 | V155: 44675
A156: LOCAL | B156: 5 | C156: Office of Budget and Management | D156: 100 | E156: Corporate Fund | F156: 1005 | G156: Office of Budget and Management | H156: 2005 | I156: Office of Budget and Management | J156: 3005 | K156: Administration | L156: 0 | N156: 1 00 | O156: 9 | P156: 9905 | Q156: Budget Director | R156: Annual | S156: 1 | T156: 1 | U156: 218280 | V156: 218280
A157: LOCAL | B157: 5 | C157: Office of Budget and Management | D157: 100 | E157: Corporate Fund | F157: 1005 | G157: Office of Budget and Management | H157: 2005 | I157: Office of Budget and Management | J157: 3005 | K157: Administration | L157: 0 | N157: X 31 | O157: 0 | P157: 9868 | Q157: First Deputy Budget Director | R157: Annual | S157: 1 | T157: 1 | U157: 199800 | V157: 199800
A158: LOCAL | B158: 5 | C158: Office of Budget and Management | D158: 100 | E158: Corporate Fund | F158: 1005 | G158: Office of Budget and Management | H158: 2005 | I158: Office of Budget and Management | J158: 3005 | K158: Administration | L158: 0 | N158: X 31 | O158: 9 | P158: 1120 | Q158: Managing Deputy Budget Director | R158: Annual | S158: 1 | T158: 1 | U158: 188400 | V158: 188400
A159: LOCAL | B159: 5 | C159: Office of Budget and Management | D159: 100 | E159: Corporate Fund | F159: 1005 | G159: Office of Budget and Management | H159: 2005 | I159: Office of Budget and Management | J159: 3005 | K159: Administration | L159: 0 | N159: BX 16 | O159: 10 | P159: 802 | Q159: Executive Administrative Assistant II | R159: Annual | S159: 1 | T159: 1 | U159: 124584 | V159: 124584
A160: LOCAL | B160: 5 | C160: Office of Budget and Management | D160: 100 | E160: Corporate Fund | F160: 1005 | G160: Office of Budget and Management | H160: 2005 | I160: Office of Budget and Management | J160: 3005 | K160: Administration | L160: 0 | N160: BX 16 | O160: 10 | P160: 802 | Q160: Executive Administrative Assistant II | R160: Annual | S160: 1 | T160: 1 | U160: 94332 | V160: 94332
A161: LOCAL | B161: 5 | C161: Office of Budget and Management | D161: 100 | E161: Corporate Fund | F161: 1005 | G161: Office of Budget and Management | H161: 2005 | I161: Office of Budget and Management | J161: 3005 | K161: Administration | L161: 0 | N161: BX 18 | O161: 20 | P161: 394 | Q161: Administrative Manager | R161: Annual | S161: 1 | T161: 1 | U161: 93384 | V161: 93384
A162: LOCAL | B162: 5 | C162: Office of Budget and Management | D162: 100 | E162: Corporate Fund | F162: 1005 | G162: Office of Budget and Management | H162: 2005 | I162: Office of Budget and Management | J162: 3005 | K162: Administration | L162: 0 | N162: 1 00 | O162: 0 | P162: 15 | Q162: Schedule Salary Adjustments | R162: Annual | S162: 0 | T162: 0 | U162: 10990 | V162: 10990
... A178: LOCAL | B178: 5 | C178: Office of Budget and Management | D178: 100 | E178: Corporate Fund | F178: 1005 | G178: Office of Budget and Management | H178: 2005 | I178: Office of Budget and Management | J178: 3015 | K178: Strategic Communications | L178: 0 | N178: 1 00 | O178: 0 | P178: 15 | Q178: Schedule Salary Adjustments | R178: Annual | S178: 0 | T178: 0 | U178: 17530 | V178: 17530
A179: LOCAL | B179: 5 | C179: Office of Budget and Management | D179: 100 | E179: Corporate Fund | F179: 1005 | G179: Office of Budget and Management | H179: 2005 | I179: Office of Budget and Management | J179: 3160 | K179: Workforce Management and Technology | L179: 4160 | M179: Compensation Control | N179: X 32 | O179: 9 | P179: 9684 | Q179: Deputy Director | R179: Annual | S179: 1 | T179: 1 | U179: 167964 | V179: 167964
A180: LOCAL | B180: 5 | C180: Office of Budget and Management | D180: 100 | E180: Corporate Fund | F180: 1005 | G180: Office of Budget and Management | H180: 2005 | I180: Office of Budget and Management | J180: 3160 | K180: Workforce Management and Technology | L180: 4160 | M180: Compensation Control | N180: BX 16 | O180: 10 | P180: 1333 | Q180: Compensation Specialist | R180: Annual | S180: 1 | T180: 1 | U180: 124584 | V180: 124584
A181: LOCAL | B181: 5 | C181: Office of Budget and Management | D181: 100 | E181: Corporate Fund | F181: 1005 | G181: Office of Budget and Management | H181: 2005 | I181: Office of Budget and Management | J181: 3160 | K181: Workforce Management and Technology | L181: 4160 | M181: Compensation Control | N181: 1 00 | O181: 0 | P181: 15 | Q181: Schedule Salary Adjustments | R181: Annual | S181: 0 | T181: 0 | U181: 1887 | V181: 1887
A182: LOCAL | B182: 5 | C182: Office of Budget and Management | D182: 100 | E182: Corporate Fund | F182: 1005 | G182: Office of Budget and Management | H182: 2005 | I182: Office of Budget and Management | J182: 3160 | K182: Workforce Management and Technology | L182: 4165 | M182: Applications | N182: X 32 | O182: 9 | P182: 9684 | Q182: Deputy Director | R182: Annual | S182: 1 | T182: 1 | U182: 167964 | V182: 167964
A183: LOCAL | B183: 5 | C183: Office of Budget and Management | D183: 100 | E183: Corporate Fund | F183: 1005 | G183: Office of Budget and Management | H183: 2005 | I183: Office of Budget and Management | J183: 3160 | K183: Workforce Management and Technology | L183: 4165 | M183: Applications | N183: GY 09 | O183: 20 | P183: 647 | Q183: Senior Programmer Analyst - Excluded | R183: Annual | S183: 1 | T183: 1 | U183: 115992 | V183: 115992
A184: LOCAL | B184: 5 | C184: Office of Budget and Management | D184: 100 | E184: Corporate Fund | F184: 1005 | G184: Office of Budget and Management | H184: 2005 | I184: Office of Budget and Management | J184: 3160 | K184: Workforce Management and Technology | L184: 4165 | M184: Applications | N184: 1 00 | O184: 0 | P184: 15 | Q184: Schedule Salary Adjustments | R184: Annual | S184: 0 | T184: 0 | U184: 1887 | V184: 1887
A185: LOCAL | B185: 5 | C185: Office of Budget and Management | D185: 100 | E185: Corporate Fund | F185: 1005 | G185: Office of Budget and Management | H185: 2005 | I185: Office of Budget and Management | J185: 3160 | K185: Workforce Management and Technology | L185: 4170 | M185: Data Analytics | N185: X 32 | O185: 9 | P185: 9656 | Q185: Deputy Budget Director | R185: Annual | S185: 1 | T185: 1 | U185: 175512 | V185: 175512
A186: LOCAL | B186: 5 | C186: Office of Budget and Management | D186: 100 | E186: Corporate Fund | F186: 1005 | G186: Office of Budget and Management | H186: 2005 | I186: Office of Budget and Management | J186: 3160 | K186: Workforce Management and Technology | L186: 4170 | M186: Data Analytics | N186: GY 08 | O186: 20 | P186: 1141 | Q186: Principal Operations Analyst | R186: Annual | S186: 2 | T186: 1 | U186: 82884 | V186: 165768
A187: LOCAL | B187: 5 | C187: Office of Budget and Management | D187: 100 | E187: Corporate Fund | F187: 1005 | G187: Office of Budget and Management | H187: 2005 | I187: Office of Budget and Management | J187: 3160 | K187: Workforce Management and Technology | L187: 4170 | M187: Data Analytics | N187: G 09 | O187: 3 | P187: 1140 | Q187: Chief Operations Analyst | R187: Annual | S187: 1 | T187: 1 | U187: 117636 | V187: 117636
A188: LOCAL | B188: 5 | C188: Office of Budget and Management | D188: 100 | E188: Corporate Fund | F188: 1005 | G188: Office of Budget and Management | H188: 2005 | I188: Office of Budget and Management | J188: 3160 | K188: Workforce Management and Technology | L188: 4170 | M188: Data Analytics | N188: X 33 | O188: 9 | P188: 1124 | Q188: Assistant Budget Director | R188: Annual | S188: 1 | T188: 1 | U188: 137532 | V188: 137532
A189: LOCAL | B189: 5 | C189: Office of Budget and Management | D189: 100 | E189: Corporate Fund | F189: 1005 | G189: Office of Budget and Management | H189: 2005 | I189: Office of Budget and Management | J189: 3160 | K189: Workforce Management and Technology | L189: 4170 | M189: Data Analytics | N189: 1 00 | O189: 0 | P189: 15 | Q189: Schedule Salary Adjustments | R189: Annual | S189: 0 | T189: 0 | U189: 4585 | V189: 4585
A190: LOCAL | B190: 5 | C190: Office of Budget and Management | D190: 100 | E190: Corporate Fund | F190: 1005 | G190: Office of Budget and Management | H190: 2005 | I190: Office of Budget and Management | J190: 3160 | K190: Workforce Management and Technology | L190: 4175 | M190: Performance Management | N190: GY 07 | O190: 20 | P190: 1125 | Q190: Performance Analyst | R190: Annual | S190: 1 | T190: 1 | U190: 85236 | V190: 85236
... A193: LOCAL | B193: 5 | C193: Office of Budget and Management | D193: 100 | E193: Corporate Fund | F193: 1005 | G193: Office of Budget and Management | H193: 2005 | I193: Office of Budget and Management | J193: 3160 | K193: Workforce Management and Technology | L193: 4175 | M193: Performance Management | N193: 1 00 | O193: 0 | P193: 15 | Q193: Schedule Salary Adjustments | R193: Annual | S193: 0 | T193: 0 | U193: 7337 | V193: 7337
A194: LOCAL | B194: 6 | C194: Department of Technology and Innovation | D194: 100 | E194: Corporate Fund | F194: 1005 | G194: Department of Technology and Innovation | H194: 2150 | I194: Bureau of Centralized Information Technology | J194: 3421 | K194: Office of CIO | L194: 0 | N194: X 32 | O194: 9 | P194: 9679 | Q194: Deputy Commissioner | R194: Annual | S194: 1 | T194: 1 | U194: 167964 | V194: 167964
A195: LOCAL | B195: 6 | C195: Department of Technology and Innovation | D195: 100 | E195: Corporate Fund | F195: 1005 | G195: Department of Technology and Innovation | H195: 2150 | I195: Bureau of Centralized Information Technology | J195: 3421 | K195: Office of CIO | L195: 0 | N195: BX 17 | O195: 10 | P195: 1431 | Q195: Senior Policy Analyst | R195: Annual | S195: 1 | T195: 1 | U195: 85128 | V195: 85128
A196: LOCAL | B196: 6 | C196: Department of Technology and Innovation | D196: 100 | E196: Corporate Fund | F196: 1005 | G196: Department of Technology and Innovation | H196: 2150 | I196: Bureau of Centralized Information Technology | J196: 3421 | K196: Office of CIO | L196: 0 | N196: B 15 | O196: 1 | P196: 1302 | Q196: Administrative Services Officer II | R196: Annual | S196: 1 | T196: 1 | U196: 143400 | V196: 143400
A197: LOCAL | B197: 6 | C197: Department of Technology and Innovation | D197: 100 | E197: Corporate Fund | F197: 1005 | G197: Department of Technology and Innovation | H197: 2150 | I197: Bureau of Centralized Information Technology | J197: 3421 | K197: Office of CIO | L197: 0 | N197: G 09 | O197: 3 | P197: 1140 | Q197: Chief Operations Analyst | R197: Annual | S197: 1 | T197: 1 | U197: 109140 | V197: 109140
A198: LOCAL | B198: 6 | C198: Department of Technology and Innovation | D198: 100 | E198: Corporate Fund | F198: 1005 | G198: Department of Technology and Innovation | H198: 2150 | I198: Bureau of Centralized Information Technology | J198: 3421 | K198: Office of CIO | L198: 0 | N198: BX 16 | O198: 10 | P198: 802 | Q198: Executive Administrative Assistant II | R198: Annual | S198: 1 | T198: 1 | U198: 124584 | V198: 124584
A199: LOCAL | B199: 6 | C199: Department of Technology and Innovation | D199: 100 | E199: Corporate Fund | F199: 1005 | G199: Department of Technology and Innovation | H199: 2150 | I199: Bureau of Centralized Information Technology | J199: 3421 | K199: Office of CIO | L199: 0 | N199: B 13 | O199: 1 | P199: 708 | Q199: FOIA Officer | R199: Annual | S199: 1 | T199: 1 | U199: 74172 | V199: 74172
A200: LOCAL | B200: 6 | C200: Department of Technology and Innovation | D200: 100 | E200: Corporate Fund | F200: 1005 | G200: Department of Technology and Innovation | H200: 2150 | I200: Bureau of Centralized Information Technology | J200: 3421 | K200: Office of CIO | L200: 0 | N200: BX 19 | O200: 20 | P200: 06J7 | Q200: Senior Project Manager - DTI | R200: Annual | S200: 1 | T200: 1 | U200: 97836 | V200: 97836
A201: LOCAL | B201: 6 | C201: Department of Technology and Innovation | D201: 100 | E201: Corporate Fund | F201: 1005 | G201: Department of Technology and Innovation | H201: 2150 | I201: Bureau of Centralized Information Technology | J201: 3421 | K201: Office of CIO | L201: 0 | N201: IT 05 | O201: 9 | P201: 06J6 | Q201: Director of Strategic Partnerships | R201: Annual | S201: 1 | T201: 1 | U201: 133836 | V201: 133836
A202: LOCAL | B202: 6 | C202: Department of Technology and Innovation | D202: 100 | E202: Corporate Fund | F202: 1005 | G202: Department of Technology and Innovation | H202: 2150 | I202: Bureau of Centralized Information Technology | J202: 3421 | K202: Office of CIO | L202: 0 | N202: 3 00 | O202: 9 | P202: 06H4 | Q202: Chief Information Officer | R202: Annual | S202: 1 | T202: 1 | U202: 227976 | V202: 227976
A203: LOCAL | B203: 6 | C203: Department of Technology and Innovation | D203: 100 | E203: Corporate Fund | F203: 1005 | G203: Department of Technology and Innovation | H203: 2150 | I203: Bureau of Centralized Information Technology | J203: 3421 | K203: Office of CIO | L203: 0 | N203: B 12 | O203: 1 | P203: 03A8 | Q203: Senior Administrative Assistant | R203: Annual | S203: 1 | T203: 1 | U203: 74172 | V203: 74172
A204: LOCAL | B204: 6 | C204: Department of Technology and Innovation | D204: 100 | E204: Corporate Fund | F204: 1005 | G204: Department of Technology and Innovation | H204: 2150 | I204: Bureau of Centralized Information Technology | J204: 3421 | K204: Office of CIO | L204: 0 | N204: X 33 | O204: 20 | P204: 383 | Q204: Director of Administrative Services | R204: Annual | S204: 1 | T204: 1 | U204: 137532 | V204: 137532
A205: LOCAL | B205: 6 | C205: Department of Technology and Innovation | D205: 100 | E205: Corporate Fund | F205: 1005 | G205: Department of Technology and Innovation | H205: 2150 | I205: Bureau of Centralized Information Technology | J205: 3421 | K205: Office of CIO | L205: 0 | N205: B 13 | O205: 1 | P205: 308 | Q205: Staff Assistant | R205: Annual | S205: 1 | T205: 1 | U205: 108576 | V205: 108576
A206: LOCAL | B206: 6 | C206: Department of Technology and Innovation | D206: 100 | E206: Corporate Fund | F206: 1005 | G206: Department of Technology and Innovation | H206: 2150 | I206: Bureau of Centralized Information Technology | J206: 3421 | K206: Office of CIO | L206: 0 | N206: G 07 | O206: 4 | P206: 124 | Q206: Finance Officer | R206: Annual | S206: 1 | T206: 1 | U206: 129636 | V206: 129636
A207: LOCAL | B207: 6 | C207: Department of Technology and Innovation | D207: 100 | E207: Corporate Fund | F207: 1005 | G207: Department of Technology and Innovation | H207: 2150 | I207: Bureau of Centralized Information Technology | J207: 3421 | K207: Office of CIO | L207: 0 | N207: X 33 | O207: 0 | P207: 118 | Q207: Director of Finance | R207: Annual | S207: 1 | T207: 1 | U207: 137532 | V207: 137532
A208: LOCAL | B208: 6 | C208: Department of Technology and Innovation | D208: 100 | E208: Corporate Fund | F208: 1005 | G208: Department of Technology and Innovation | H208: 2150 | I208: Bureau of Centralized Information Technology | J208: 3421 | K208: Office of CIO | L208: 0 | N208: B 13 | O208: 4 | P208: 110 | Q208: Accountant | R208: Annual | S208: 1 | T208: 1 | U208: 74172 | V208: 74172
A209: LOCAL | B209: 6 | C209: Department of Technology and Innovation | D209: 100 | E209: Corporate Fund | F209: 1005 | G209: Department of Technology and Innovation | H209: 2150 | I209: Bureau of Centralized Information Technology | J209: 3421 | K209: Office of CIO | L209: 0 | N209: B 11 | O209: 1 | P209: 109 | Q209: Accounting Technician | R209: Annual | S209: 2 | T209: 1 | U209: 58764 | V209: 117528
A210: LOCAL | B210: 6 | C210: Department of Technology and Innovation | D210: 100 | E210: Corporate Fund | F210: 1005 | G210: Department of Technology and Innovation | H210: 2150 | I210: Bureau of Centralized Information Technology | J210: 3421 | K210: Office of CIO | L210: 0 | N210: 1 00 | O210: 0 | P210: 15 | Q210: Schedule Salary Adjustments | R210: Annual | S210: 0 | T210: 0 | U210: 27687 | V210: 27687
A211: LOCAL | B211: 6 | C211: Department of Technology and Innovation | D211: 100 | E211: Corporate Fund | F211: 1005 | G211: Department of Technology and Innovation | H211: 2150 | I211: Bureau of Centralized Information Technology | J211: 3425 | K211: IT Planning | L211: 0 | N211: B 15 | O211: 1 | P211: 1572 | Q211: Chief Contract Expediter | R211: Annual | S211: 1 | T211: 1 | U211: 89244 | V211: 89244
A212: LOCAL | B212: 6 | C212: Department of Technology and Innovation | D212: 100 | E212: Corporate Fund | F212: 1005 | G212: Department of Technology and Innovation | H212: 2150 | I212: Bureau of Centralized Information Technology | J212: 3425 | K212: IT Planning | L212: 0 | N212: B 13 | O212: 1 | P212: 1482 | Q212: Contract Review Specialist II | R212: Annual | S212: 1 | T212: 1 | U212: 77640 | V212: 77640
A213: LOCAL | B213: 6 | C213: Department of Technology and Innovation | D213: 100 | E213: Corporate Fund | F213: 1005 | G213: Department of Technology and Innovation | H213: 2150 | I213: Bureau of Centralized Information Technology | J213: 3425 | K213: IT Planning | L213: 0 | N213: BX 17 | O213: 20 | P213: 06K3 | Q213: eDiscovery Specialist | R213: Annual | S213: 1 | T213: 1 | U213: 85128 | V213: 85128
A214: LOCAL | B214: 6 | C214: Department of Technology and Innovation | D214: 100 | E214: Corporate Fund | F214: 1005 | G214: Department of Technology and Innovation | H214: 2150 | I214: Bureau of Centralized Information Technology | J214: 3425 | K214: IT Planning | L214: 0 | N214: IT 06 | O214: 20 | P214: 06H5 | Q214: Head Of Planning | R214: Annual | S214: 1 | T214: 1 | U214: 204516 | V214: 204516
A215: LOCAL | B215: 6 | C215: Department of Technology and Innovation | D215: 100 | E215: Corporate Fund | F215: 1005 | G215: Department of Technology and Innovation | H215: 2150 | I215: Bureau of Centralized Information Technology | J215: 3425 | K215: IT Planning | L215: 0 | N215: IT 05 | O215: 20 | P215: 06H1 | Q215: Enterprise Architecture Lead | R215: Annual | S215: 1 | T215: 1 | U215: 173160 | V215: 173160
A216: LOCAL | B216: 6 | C216: Department of Technology and Innovation | D216: 100 | E216: Corporate Fund | F216: 1005 | G216: Department of Technology and Innovation | H216: 2150 | I216: Bureau of Centralized Information Technology | J216: 3425 | K216: IT Planning | L216: 0 | N216: B 14 | O216: 1 | P216: 06C6 | Q216: Vendor/License Specialist | R216: Annual | S216: 2 | T216: 1 | U216: 75336 | V216: 150672
A217: LOCAL | B217: 6 | C217: Department of Technology and Innovation | D217: 100 | E217: Corporate Fund | F217: 1005 | G217: Department of Technology and Innovation | H217: 2150 | I217: Bureau of Centralized Information Technology | J217: 3425 | K217: IT Planning | L217: 0 | N217: BX 19 | O217: 20 | P217: 06C5 | Q217: Vendor/License Specialist Lead | R217: Annual | S217: 1 | T217: 1 | U217: 118956 | V217: 118956
A218: LOCAL | B218: 6 | C218: Department of Technology and Innovation | D218: 100 | E218: Corporate Fund | F218: 1005 | G218: Department of Technology and Innovation | H218: 2150 | I218: Bureau of Centralized Information Technology | J218: 3425 | K218: IT Planning | L218: 0 | N218: B 14 | O218: 1 | P218: 06C3 | Q218: Business Analyst | R218: Annual | S218: 1 | T218: 1 | U218: 75336 | V218: 75336
A219: LOCAL | B219: 6 | C219: Department of Technology and Innovation | D219: 100 | E219: Corporate Fund | F219: 1005 | G219: Department of Technology and Innovation | H219: 2150 | I219: Bureau of Centralized Information Technology | J219: 3425 | K219: IT Planning | L219: 0 | N219: IT 01 | O219: 20 | P219: 06B9 | Q219: Governance Manager | R219: Annual | S219: 1 | T219: 1 | U219: 110940 | V219: 110940
A220: LOCAL | B220: 6 | C220: Department of Technology and Innovation | D220: 100 | E220: Corporate Fund | F220: 1005 | G220: Department of Technology and Innovation | H220: 2150 | I220: Bureau of Centralized Information Technology | J220: 3425 | K220: IT Planning | L220: 0 | N220: BX 19 | O220: 20 | P220: 06B7 | Q220: Organizational Change Management Lead | R220: Annual | S220: 1 | T220: 1 | U220: 97836 | V220: 97836
A221: LOCAL | B221: 6 | C221: Department of Technology and Innovation | D221: 100 | E221: Corporate Fund | F221: 1005 | G221: Department of Technology and Innovation | H221: 2150 | I221: Bureau of Centralized Information Technology | J221: 3425 | K221: IT Planning | L221: 0 | N221: IT 01 | O221: 20 | P221: 06B4 | Q221: Strategic Planning Manager | R221: Annual | S221: 1 | T221: 1 | U221: 120144 | V221: 120144
A222: LOCAL | B222: 6 | C222: Department of Technology and Innovation | D222: 100 | E222: Corporate Fund | F222: 1005 | G222: Department of Technology and Innovation | H222: 2150 | I222: Bureau of Centralized Information Technology | J222: 3425 | K222: IT Planning | L222: 0 | N222: G 10 | O222: 4 | P222: 06B3 | Q222: Solutions Architect | R222: Annual | S222: 1 | T222: 1 | U222: 153228 | V222: 153228
A223: LOCAL | B223: 6 | C223: Department of Technology and Innovation | D223: 100 | E223: Corporate Fund | F223: 1005 | G223: Department of Technology and Innovation | H223: 2150 | I223: Bureau of Centralized Information Technology | J223: 3425 | K223: IT Planning | L223: 0 | N223: G 10 | O223: 4 | P223: 06B3 | Q223: Solutions Architect | R223: Annual | S223: 1 | T223: 1 | U223: 119244 | V223: 119244
A224: LOCAL | B224: 6 | C224: Department of Technology and Innovation | D224: 100 | E224: Corporate Fund | F224: 1005 | G224: Department of Technology and Innovation | H224: 2150 | I224: Bureau of Centralized Information Technology | J224: 3425 | K224: IT Planning | L224: 0 | N224: IT 03 | O224: 20 | P224: 06B1 | Q224: Enterprise Architect | R224: Annual | S224: 1 | T224: 1 | U224: 140868 | V224: 140868
A225: LOCAL | B225: 6 | C225: Department of Technology and Innovation | D225: 100 | E225: Corporate Fund | F225: 1005 | G225: Department of Technology and Innovation | H225: 2150 | I225: Bureau of Centralized Information Technology | J225: 3425 | K225: IT Planning | L225: 0 | N225: B 16 | O225: 4 | P225: 345 | Q225: Contracts Coordinator | R225: Annual | S225: 1 | T225: 1 | U225: 130668 | V225: 130668
A226: LOCAL | B226: 6 | C226: Department of Technology and Innovation | D226: 100 | E226: Corporate Fund | F226: 1005 | G226: Department of Technology and Innovation | H226: 2150 | I226: Bureau of Centralized Information Technology | J226: 3425 | K226: IT Planning | L226: 0 | N226: 1 00 | O226: 0 | P226: 15 | Q226: Schedule Salary Adjustments | R226: Annual | S226: 0 | T226: 0 | U226: 23805 | V226: 23805
A227: LOCAL | B227: 6 | C227: Department of Technology and Innovation | D227: 100 | E227: Corporate Fund | F227: 1005 | G227: Department of Technology and Innovation | H227: 2150 | I227: Bureau of Centralized Information Technology | J227: 3430 | K227: IT Delivery | L227: 0 | N227: G 09 | O227: 4 | P227: 06L2 | Q227: Principal Engineer | R227: Annual | S227: 4 | T227: 1 | U227: 154764 | V227: 619056
A228: LOCAL | B228: 6 | C228: Department of Technology and Innovation | D228: 100 | E228: Corporate Fund | F228: 1005 | G228: Department of Technology and Innovation | H228: 2150 | I228: Bureau of Centralized Information Technology | J228: 3430 | K228: IT Delivery | L228: 0 | N228: G 09 | O228: 4 | P228: 06L2 | Q228: Principal Engineer | R228: Annual | S228: 1 | T228: 1 | U228: 128316 | V228: 128316
A229: LOCAL | B229: 6 | C229: Department of Technology and Innovation | D229: 100 | E229: Corporate Fund | F229: 1005 | G229: Department of Technology and Innovation | H229: 2150 | I229: Bureau of Centralized Information Technology | J229: 3430 | K229: IT Delivery | L229: 0 | N229: G 09 | O229: 4 | P229: 06L2 | Q229: Principal Engineer | R229: Annual | S229: 2 | T229: 1 | U229: 109140 | V229: 218280
A230: LOCAL | B230: 6 | C230: Department of Technology and Innovation | D230: 100 | E230: Corporate Fund | F230: 1005 | G230: Department of Technology and Innovation | H230: 2150 | I230: Bureau of Centralized Information Technology | J230: 3430 | K230: IT Delivery | L230: 0 | N230: B 17 | O230: 1 | P230: 06K8 | Q230: Principal Data Analyst | R230: Annual | S230: 1 | T230: 1 | U230: 164880 | V230: 164880
A231: LOCAL | B231: 6 | C231: Department of Technology and Innovation | D231: 100 | E231: Corporate Fund | F231: 1005 | G231: Department of Technology and Innovation | H231: 2150 | I231: Bureau of Centralized Information Technology | J231: 3430 | K231: IT Delivery | L231: 0 | N231: B 17 | O231: 1 | P231: 06K8 | Q231: Principal Data Analyst | R231: Annual | S231: 2 | T231: 1 | U231: 99480 | V231: 198960
A232: LOCAL | B232: 6 | C232: Department of Technology and Innovation | D232: 100 | E232: Corporate Fund | F232: 1005 | G232: Department of Technology and Innovation | H232: 2150 | I232: Bureau of Centralized Information Technology | J232: 3430 | K232: IT Delivery | L232: 0 | N232: B 15 | O232: 1 | P232: 06K7 | Q232: Senior Data Analyst | R232: Annual | S232: 3 | T232: 1 | U232: 82644 | V232: 247932
A233: LOCAL | B233: 6 | C233: Department of Technology and Innovation | D233: 100 | E233: Corporate Fund | F233: 1005 | G233: Department of Technology and Innovation | H233: 2150 | I233: Bureau of Centralized Information Technology | J233: 3430 | K233: IT Delivery | L233: 0 | N233: BX 18 | O233: 20 | P233: 06K4 | Q233: Project Manager - DTI | R233: Annual | S233: 1 | T233: 1 | U233: 136692 | V233: 136692
A234: LOCAL | B234: 6 | C234: Department of Technology and Innovation | D234: 100 | E234: Corporate Fund | F234: 1005 | G234: Department of Technology and Innovation | H234: 2150 | I234: Bureau of Centralized Information Technology | J234: 3430 | K234: IT Delivery | L234: 0 | N234: BX 18 | O234: 20 | P234: 06K4 | Q234: Project Manager - DTI | R234: Annual | S234: 1 | T234: 1 | U234: 89112 | V234: 89112
A235: LOCAL | B235: 6 | C235: Department of Technology and Innovation | D235: 100 | E235: Corporate Fund | F235: 1005 | G235: Department of Technology and Innovation | H235: 2150 | I235: Bureau of Centralized Information Technology | J235: 3430 | K235: IT Delivery | L235: 0 | N235: BX 19 | O235: 20 | P235: 06J7 | Q235: Senior Project Manager - DTI | R235: Annual | S235: 2 | T235: 1 | U235: 118956 | V235: 237912
A236: LOCAL | B236: 6 | C236: Department of Technology and Innovation | D236: 100 | E236: Corporate Fund | F236: 1005 | G236: Department of Technology and Innovation | H236: 2150 | I236: Bureau of Centralized Information Technology | J236: 3430 | K236: IT Delivery | L236: 0 | N236: BX 19 | O236: 20 | P236: 06J7 | Q236: Senior Project Manager - DTI | R236: Annual | S236: 1 | T236: 1 | U236: 113568 | V236: 113568
A237: LOCAL | B237: 6 | C237: Department of Technology and Innovation | D237: 100 | E237: Corporate Fund | F237: 1005 | G237: Department of Technology and Innovation | H237: 2150 | I237: Bureau of Centralized Information Technology | J237: 3430 | K237: IT Delivery | L237: 0 | N237: BX 19 | O237: 20 | P237: 06J7 | Q237: Senior Project Manager - DTI | R237: Annual | S237: 3 | T237: 1 | U237: 102444 | V237: 307332
A238: LOCAL | B238: 6 | C238: Department of Technology and Innovation | D238: 100 | E238: Corporate Fund | F238: 1005 | G238: Department of Technology and Innovation | H238: 2150 | I238: Bureau of Centralized Information Technology | J238: 3430 | K238: IT Delivery | L238: 0 | N238: B 16 | O238: 1 | P238: 06J4 | Q238: Web Developer | R238: Annual | S238: 1 | T238: 1 | U238: 143400 | V238: 143400
... A253: LOCAL | B253: 6 | C253: Department of Technology and Innovation | D253: 100 | E253: Corporate Fund | F253: 1005 | G253: Department of Technology and Innovation | H253: 2150 | I253: Bureau of Centralized Information Technology | J253: 3430 | K253: IT Delivery | L253: 0 | N253: BX 19 | O253: 20 | P253: 06F1 | Q253: Content Manager Lead | R253: Annual | S253: 1 | T253: 1 | U253: 97836 | V253: 97836
A254: LOCAL | B254: 6 | C254: Department of Technology and Innovation | D254: 100 | E254: Corporate Fund | F254: 1005 | G254: Department of Technology and Innovation | H254: 2150 | I254: Bureau of Centralized Information Technology | J254: 3430 | K254: IT Delivery | L254: 0 | N254: IT 02 | O254: 20 | P254: 6000000000 | Q254: Web Development Lead | R254: Annual | S254: 1 | T254: 1 | U254: 120144 | V254: 120144
A255: LOCAL | B255: 6 | C255: Department of Technology and Innovation | D255: 100 | E255: Corporate Fund | F255: 1005 | G255: Department of Technology and Innovation | H255: 2150 | I255: Bureau of Centralized Information Technology | J255: 3430 | K255: IT Delivery | L255: 0 | N255: IT 04 | O255: 20 | P255: 600000000 | Q255: Data Science Lead | R255: Annual | S255: 1 | T255: 1 | U255: 140868 | V255: 140868
A256: LOCAL | B256: 6 | C256: Department of Technology and Innovation | D256: 100 | E256: Corporate Fund | F256: 1005 | G256: Department of Technology and Innovation | H256: 2150 | I256: Bureau of Centralized Information Technology | J256: 3430 | K256: IT Delivery | L256: 0 | N256: IT 04 | O256: 20 | P256: 60000000 | Q256: Data Portal Lead | R256: Annual | S256: 1 | T256: 1 | U256: 166860 | V256: 166860
A257: LOCAL | B257: 6 | C257: Department of Technology and Innovation | D257: 100 | E257: Corporate Fund | F257: 1005 | G257: Department of Technology and Innovation | H257: 2150 | I257: Bureau of Centralized Information Technology | J257: 3430 | K257: IT Delivery | L257: 0 | N257: B 16 | O257: 1 | P257: 06D6 | Q257: Web Designer | R257: Annual | S257: 2 | T257: 1 | U257: 90732 | V257: 181464
A258: LOCAL | B258: 6 | C258: Department of Technology and Innovation | D258: 100 | E258: Corporate Fund | F258: 1005 | G258: Department of Technology and Innovation | H258: 2150 | I258: Bureau of Centralized Information Technology | J258: 3430 | K258: IT Delivery | L258: 0 | N258: B 14 | O258: 1 | P258: 06C9 | Q258: Content Manager | R258: Annual | S258: 2 | T258: 1 | U258: 75336 | V258: 150672
A259: LOCAL | B259: 6 | C259: Department of Technology and Innovation | D259: 100 | E259: Corporate Fund | F259: 1005 | G259: Department of Technology and Innovation | H259: 2150 | I259: Bureau of Centralized Information Technology | J259: 3430 | K259: IT Delivery | L259: 0 | N259: G 10 | O259: 4 | P259: 06C8 | Q259: Application Delivery Manager | R259: Annual | S259: 1 | T259: 1 | U259: 164808 | V259: 164808
A260: LOCAL | B260: 6 | C260: Department of Technology and Innovation | D260: 100 | E260: Corporate Fund | F260: 1005 | G260: Department of Technology and Innovation | H260: 2150 | I260: Bureau of Centralized Information Technology | J260: 3430 | K260: IT Delivery | L260: 0 | N260: G 10 | O260: 4 | P260: 06C8 | Q260: Application Delivery Manager | R260: Annual | S260: 1 | T260: 1 | U260: 134184 | V260: 134184
A261: LOCAL | B261: 6 | C261: Department of Technology and Innovation | D261: 100 | E261: Corporate Fund | F261: 1005 | G261: Department of Technology and Innovation | H261: 2150 | I261: Bureau of Centralized Information Technology | J261: 3430 | K261: IT Delivery | L261: 0 | N261: G 10 | O261: 4 | P261: 06C7 | Q261: Data Architect | R261: Annual | S261: 1 | T261: 1 | U261: 160020 | V261: 160020
A262: LOCAL | B262: 6 | C262: Department of Technology and Innovation | D262: 100 | E262: Corporate Fund | F262: 1005 | G262: Department of Technology and Innovation | H262: 2150 | I262: Bureau of Centralized Information Technology | J262: 3430 | K262: IT Delivery | L262: 0 | N262: B 14 | O262: 1 | P262: 06C3 | Q262: Business Analyst | R262: Annual | S262: 1 | T262: 1 | U262: 130668 | V262: 130668
A263: LOCAL | B263: 6 | C263: Department of Technology and Innovation | D263: 100 | E263: Corporate Fund | F263: 1005 | G263: Department of Technology and Innovation | H263: 2150 | I263: Bureau of Centralized Information Technology | J263: 3430 | K263: IT Delivery | L263: 0 | N263: B 14 | O263: 1 | P263: 06C3 | Q263: Business Analyst | R263: Annual | S263: 6 | T263: 1 | U263: 75336 | V263: 452016
...
